checkfile/__init__.py
checkfile-85.43.57.dist-info/METADATA
checkfile-85.43.57.dist-info/WHEEL
checkfile-85.43.57.dist-info/top_level.txt
checkfile-85.43.57.dist-info/RECORD
