Metadata-Version: 2.1
Name: checkfile
Version: 85.43.57
Summary: A Python package that stops files from being edited.
Author: JZ Enterprises
Requires-Python: >=3.6
